jpipe/__init__.py
jpipe/cmd/__init__.py
jpipe/cmd/main.py
jpipe/jp/__init__.py
jpipe/jp/main.py
jpipe/jpp/__init__.py
jpipe/jpp/main.py
jpipe-0.2.0.dist-info/LICENSE
jpipe-0.2.0.dist-info/METADATA
jpipe-0.2.0.dist-info/WHEEL
jpipe-0.2.0.dist-info/entry_points.txt
jpipe-0.2.0.dist-info/top_level.txt
jpipe-0.2.0.dist-info/RECORD
