Metadata-Version: 2.1
Name: jpipe
Version: 0.2.0
Summary: A python implementation of the jp CLI for JMESPath
Home-page: https://github.com/pipebus/jpipe
Author: Zac Medico
Author-email: <zmedico@gmail.com>
License: UNKNOWN
Project-URL: Bug Tracker, https://github.com/pipebus/jpipe/issues
Platform: UNKNOWN
Classifier: License :: OSI Approved :: Apache Software License
Classifier: Operating System :: POSIX
Classifier: Programming Language :: Python :: 3
Classifier: Programming Language :: Unix Shell
Requires-Python: >=3.6
License-File: LICENSE
Requires-Dist: jmespath
